basicdweet/__init__.py
basicdweet/basicdweet.py
basicdweet-0.4.0.dist-info/LICENSE
basicdweet-0.4.0.dist-info/METADATA
basicdweet-0.4.0.dist-info/WHEEL
basicdweet-0.4.0.dist-info/top_level.txt
basicdweet-0.4.0.dist-info/RECORD
