Metadata-Version: 2.1
Name: basicdweet
Version: 0.4.0
Summary: Basic APIs of the free dweet service.
Author-email: Quan Lin <jacklinquan@gmail.com>
License: MIT License
Project-URL: Homepage, https://github.com/jacklinquan/basicdweet
Keywords: dweet
Classifier: License :: OSI Approved :: MIT License
Classifier: Programming Language :: Python
Classifier: Programming Language :: Python :: 3
Requires-Python: >=3.7
License-File: LICENSE
Requires-Dist: requests
Provides-Extra: aiohttp
Requires-Dist: aiohttp ; extra == 'aiohttp'
Provides-Extra: dev
Requires-Dist: aiohttp ; extra == 'dev'
Requires-Dist: black ; extra == 'dev'
Requires-Dist: pytest ; extra == 'dev'
